openprovider/__init__.py
openprovider/__main__.py
openprovider/api.py
openprovider/exceptions.py
openprovider/models.py
openprovider/response.py
openprovider/util.py
openprovider/data/__init__.py
openprovider/data/exception_map.py
openprovider/data/sslcerts.py
openprovider/modules/__init__.py
openprovider/modules/common.py
openprovider/modules/customer.py
openprovider/modules/domain.py
openprovider/modules/email.py
openprovider/modules/extension.py
openprovider/modules/financial.py
openprovider/modules/nameserver.py
openprovider/modules/nsgroup.py
openprovider/modules/reseller.py
openprovider/modules/ssl.py
openprovider.py-0.10.4.dist-info/DESCRIPTION.rst
openprovider.py-0.10.4.dist-info/METADATA
openprovider.py-0.10.4.dist-info/RECORD
openprovider.py-0.10.4.dist-info/WHEEL
openprovider.py-0.10.4.dist-info/metadata.json
openprovider.py-0.10.4.dist-info/pbr.json
openprovider.py-0.10.4.dist-info/top_level.txt
