Metadata-Version: 2.0
Name: openprovider.py
Version: 0.10.4
Summary: An unofficial library for the OpenProvider API
Home-page: https://github.com/AntagonistHQ/openprovider.py
Author: Antagonist B.V.
Author-email: info@antagonist.nl
License: LICENSE.rst
Platform: UNKNOWN
Requires-Dist: lxml (>=3.3.5)
Requires-Dist: requests (>=2.3.0,<=2.5.1)
